MANIFEST.in
README.md
consul-requirements.txt
dynamodb-requirements.txt
redis-requirements.txt
requirements.txt
setup.py
test-requirements.txt
ldclient/__init__.py
ldclient/client.py
ldclient/config.py
ldclient/event_processor.py
ldclient/event_summarizer.py
ldclient/feature_requester.py
ldclient/feature_store.py
ldclient/feature_store_helpers.py
ldclient/file_data_source.py
ldclient/fixed_thread_pool.py
ldclient/flag.py
ldclient/flags_state.py
ldclient/integrations.py
ldclient/interfaces.py
ldclient/lru_cache.py
ldclient/memoized_value.py
ldclient/operators.py
ldclient/polling.py
ldclient/redis_feature_store.py
ldclient/repeating_timer.py
ldclient/rwlock.py
ldclient/sse_client.py
ldclient/streaming.py
ldclient/user_filter.py
ldclient/util.py
ldclient/version.py
ldclient/versioned_data_kind.py
ldclient/impl/__init__.py
ldclient/impl/stubs.py
ldclient/impl/integrations/__init__.py
ldclient/impl/integrations/consul/__init__.py
ldclient/impl/integrations/consul/consul_feature_store.py
ldclient/impl/integrations/dynamodb/__init__.py
ldclient/impl/integrations/dynamodb/dynamodb_feature_store.py
ldclient/impl/integrations/files/__init__.py
ldclient/impl/integrations/files/file_data_source.py
ldclient/impl/integrations/redis/__init__.py
ldclient/impl/integrations/redis/redis_feature_store.py
ldclient_py.egg-info/PKG-INFO
ldclient_py.egg-info/SOURCES.txt
ldclient_py.egg-info/dependency_links.txt
ldclient_py.egg-info/requires.txt
ldclient_py.egg-info/top_level.txt
testing/__init__.py
testing/stub_util.py
testing/sync_util.py
testing/test_config.py
testing/test_event_processor.py
testing/test_event_summarizer.py
testing/test_feature_store.py
testing/test_feature_store_helpers.py
testing/test_file_data_source.py
testing/test_flag.py
testing/test_flags_state.py
testing/test_init.py
testing/test_integration_init.py
testing/test_integration_ldclient.py
testing/test_ldclient.py
testing/test_ldclient_evaluation.py
testing/test_lru_cache.py
testing/test_operators.py
testing/test_polling_processor.py
testing/test_segment.py
testing/test_user_filter.py