Metadata-Version: 2.1
Name: ldclient-py
Version: 6.9.0
Summary: LaunchDarkly SDK for Python
Home-page: https://github.com/launchdarkly/python-client
Author: LaunchDarkly
Author-email: team@launchdarkly.com
License: UNKNOWN
Platform: UNKNOWN
Classifier: Intended Audience :: Developers
Classifier: License :: OSI Approved :: Apache Software License
Classifier: Operating System :: OS Independent
Classifier: Programming Language :: Python :: 2
Classifier: Programming Language :: Python :: 2.7
Classifier: Programming Language :: Python :: 3
Classifier: Programming Language :: Python :: 3.3
Classifier: Programming Language :: Python :: 3.4
Classifier: Programming Language :: Python :: 3.5
Classifier: Programming Language :: Python :: 3.6
Classifier: Programming Language :: Python :: 3.7
Classifier: Topic :: Software Development
Classifier: Topic :: Software Development :: Libraries
Provides-Extra: dynamodb
Provides-Extra: consul
Provides-Extra: redis
